flyteplugins/dask/__init__.py
flyteplugins/dask/task.py
flyteplugins_dask-2.0.0b53.dist-info/METADATA
flyteplugins_dask-2.0.0b53.dist-info/WHEEL
flyteplugins_dask-2.0.0b53.dist-info/top_level.txt
flyteplugins_dask-2.0.0b53.dist-info/RECORD
