Metadata-Version: 2.4
Name: flyteplugins-dask
Version: 2.0.0b53
Summary: Dask plugin for flyte
Author-email: Kevin Su <pingsutw@users.noreply.github.com>
Requires-Python: >=3.10
Requires-Dist: dask[distributed]>=2022.10.2
Requires-Dist: flyte>v2.0.0b23
Requires-Dist: bokeh
